[
  {
    "Total_mv": 739064.1551,
    "Pe": 227.1064,
    "Pe_ttm": 227.1064,
    "TsCode": "002232.SZ",
    "TradeDate": "20260423",
    "Open": 18.25,
    "High": 18.39,
    "Low": 18.03,
    "Close": 18.09,
    "Vol": 34369.0,
    "Amount": 62329.041,
    "PctChg": -1.4706,
    "macdData": null,
    "kdjData": null,
    "FiveDayAvgPrice": 0.0,
    "TenDayAvgPrice": 0.0,
    "TwentyDayAvgPrice": 0.0,
    "FiveDayAvgVol": 0.0,
    "TenDayAvgVol": 0.0,
    "TwentyDayAvgVol": 0.0,
    "Concentration70": 6.01,
    "Concentration90": 8.99,
    "ConcentrationPrice": 17.8
  },
  {
    "Total_mv": 750094.9634,
    "Pe": 230.496,
    "Pe_ttm": 230.496,
    "TsCode": "002232.SZ",
    "TradeDate": "20260422",
    "Open": 18.29,
    "High": 18.36,
    "Low": 18.03,
    "Close": 18.36,
    "Vol": 39408.0,
    "Amount": 71879.289,
    "PctChg": 0.7131,
    "macdData": null,
    "kdjData": null,
    "FiveDayAvgPrice": 0.0,
    "TenDayAvgPrice": 0.0,
    "TwentyDayAvgPrice": 0.0,
    "FiveDayAvgVol": 0.0,
    "TenDayAvgVol": 0.0,
    "TwentyDayAvgVol": 0.0,
    "Concentration70": 0.0,
    "Concentration90": 0.0,
    "ConcentrationPrice": 0.0
  },
  {
    "Total_mv": 744783.8335,
    "Pe": 228.864,
    "Pe_ttm": 228.864,
    "TsCode": "002232.SZ",
    "TradeDate": "20260421",
    "Open": 18.35,
    "High": 18.49,
    "Low": 18.11,
    "Close": 18.23,
    "Vol": 37751.0,
    "Amount": 68691.058,
    "PctChg": -1.4062,
    "macdData": null,
    "kdjData": null,
    "FiveDayAvgPrice": 18.187999999999995,
    "TenDayAvgPrice": 17.976999999999997,
    "TwentyDayAvgPrice": 17.669500000000006,
    "FiveDayAvgVol": 48593.104000000007,
    "TenDayAvgVol": 44613.621000000014,
    "TwentyDayAvgVol": 43272.904999999992,
    "Concentration70": 5.88,
    "Concentration90": 8.99,
    "ConcentrationPrice": 17.8
  },
  {
    "Total_mv": 755406.0933,
    "Pe": 232.1281,
    "Pe_ttm": 232.1281,
    "TsCode": "002232.SZ",
    "TradeDate": "20260420",
    "Open": 18.3,
    "High": 18.5,
    "Low": 18.26,
    "Close": 18.49,
    "Vol": 46877.51,
    "Amount": 86455.316,
    "PctChg": 0.9279,
    "macdData": null,
    "kdjData": null,
    "FiveDayAvgPrice": 18.127999999999993,
    "TenDayAvgPrice": 17.891,
    "TwentyDayAvgPrice": 17.567500000000003,
    "FiveDayAvgVol": 48736.526000000005,
    "TenDayAvgVol": 43195.521000000015,
    "TwentyDayAvgVol": 44348.342999999993,
    "Concentration70": 0.0,
    "Concentration90": 0.0,
    "ConcentrationPrice": 0.0
  },
  {
    "Total_mv": 748460.7696,
    "Pe": 229.9939,
    "Pe_ttm": 229.9939,
    "TsCode": "002232.SZ",
    "TradeDate": "20260417",
    "Open": 18.1,
    "High": 18.4,
    "Low": 18.06,
    "Close": 18.32,
    "Vol": 61569.0,
    "Amount": 112445.606,
    "PctChg": 0.8811,
    "macdData": null,
    "kdjData": null,
    "FiveDayAvgPrice": 17.993999999999993,
    "TenDayAvgPrice": 17.749999999999996,
    "TwentyDayAvgPrice": 17.495000000000005,
    "FiveDayAvgVol": 47721.424000000006,
    "TenDayAvgVol": 41245.272000000012,
    "TwentyDayAvgVol": 44771.664499999992,
    "Concentration70": 0.0,
    "Concentration90": 0.0,
    "ConcentrationPrice": 0.0
  },
  {
    "Total_mv": 741923.9943,
    "Pe": 227.9852,
    "Pe_ttm": 227.9852,
    "TsCode": "002232.SZ",
    "TradeDate": "20260416",
    "Open": 17.8,
    "High": 18.2,
    "Low": 17.77,
    "Close": 18.16,
    "Vol": 65084.01,
    "Amount": 117401.412,
    "PctChg": 2.3675,
    "macdData": null,
    "kdjData": null,
    "FiveDayAvgPrice": 17.843999999999994,
    "TenDayAvgPrice": 17.677999999999997,
    "TwentyDayAvgPrice": 17.475500000000004,
    "FiveDayAvgVol": 43284.76,
    "TenDayAvgVol": 38658.87000000001,
    "TwentyDayAvgVol": 43088.114499999989,
    "Concentration70": 0.0,
    "Concentration90": 0.0,
    "ConcentrationPrice": 0.0
  },
  {
    "Total_mv": 724764.9592,
    "Pe": 222.7124,
    "Pe_ttm": 222.7124,
    "TsCode": "002232.SZ",
    "TradeDate": "20260415",
    "Open": 17.94,
    "High": 18.01,
    "Low": 17.7,
    "Close": 17.74,
    "Vol": 31684.0,
    "Amount": 56575.947,
    "PctChg": -1.0597,
    "macdData": null,
    "kdjData": null,
    "FiveDayAvgPrice": 17.723999999999997,
    "TenDayAvgPrice": 17.639999999999997,
    "TwentyDayAvgPrice": 17.471000000000004,
    "FiveDayAvgVol": 37601.958,
    "TenDayAvgVol": 36089.293000000012,
    "TwentyDayAvgVol": 41467.568999999989,
    "Concentration70": 0.0,
    "Concentration90": 0.0,
    "ConcentrationPrice": 0.0
  },
  {
    "Total_mv": 732527.3798,
    "Pe": 225.0977,
    "Pe_ttm": 225.0977,
    "TsCode": "002232.SZ",
    "TradeDate": "20260414",
    "Open": 17.98,
    "High": 18.1,
    "Low": 17.74,
    "Close": 17.93,
    "Vol": 38468.11,
    "Amount": 68830.444,
    "PctChg": 0.6173,
    "macdData": null,
    "kdjData": null,
    "FiveDayAvgPrice": 17.766,
    "TenDayAvgPrice": 17.644,
    "TwentyDayAvgPrice": 17.466,
    "FiveDayAvgVol": 40634.138,
    "TenDayAvgVol": 38886.38900000001,
    "TwentyDayAvgVol": 41352.569499999991,
    "Concentration70": 0.0,
    "Concentration90": 0.0,
    "ConcentrationPrice": 0.0
  },
  {
    "Total_mv": 728033.3468,
    "Pe": 223.7167,
    "Pe_ttm": 223.7167,
    "TsCode": "002232.SZ",
    "TradeDate": "20260413",
    "Open": 17.69,
    "High": 17.9,
    "Low": 17.59,
    "Close": 17.82,
    "Vol": 41802.0,
    "Amount": 74214.909,
    "PctChg": 1.4229,
    "macdData": null,
    "kdjData": null,
    "FiveDayAvgPrice": 17.653999999999996,
    "TenDayAvgPrice": 17.651999999999994,
    "TwentyDayAvgPrice": 17.4645,
    "FiveDayAvgVol": 37654.516,
    "TenDayAvgVol": 44534.371000000014,
    "TwentyDayAvgVol": 40672.681999999986,
    "Concentration70": 0.0,
    "Concentration90": 0.0,
    "ConcentrationPrice": 0.0
  },
  {
    "Total_mv": 717819.6354,
    "Pe": 220.5782,
    "Pe_ttm": 220.5782,
    "TsCode": "002232.SZ",
    "TradeDate": "20260410",
    "Open": 17.7,
    "High": 17.82,
    "Low": 17.57,
    "Close": 17.57,
    "Vol": 39385.68,
    "Amount": 69659.754,
    "PctChg": 0.0569,
    "macdData": null,
    "kdjData": null,
    "FiveDayAvgPrice": 17.505999999999993,
    "TenDayAvgPrice": 17.592999999999996,
    "TwentyDayAvgPrice": 17.462,
    "FiveDayAvgVol": 34769.12,
    "TenDayAvgVol": 44099.025000000009,
    "TwentyDayAvgVol": 40076.32499999999,
    "Concentration70": 0.0,
    "Concentration90": 0.0,
    "ConcentrationPrice": 0.0
  },
  {
    "Total_mv": 717411.087,
    "Pe": 220.4526,
    "Pe_ttm": 220.4526,
    "TsCode": "002232.SZ",
    "TradeDate": "20260409",
    "Open": 17.75,
    "High": 17.87,
    "Low": 17.5,
    "Close": 17.56,
    "Vol": 36670.0,
    "Amount": 64693.74,
    "PctChg": -2.1727,
    "macdData": null,
    "kdjData": null,
    "FiveDayAvgPrice": 17.511999999999993,
    "TenDayAvgPrice": 17.518999999999995,
    "TwentyDayAvgPrice": 17.481,
    "FiveDayAvgVol": 34032.98,
    "TenDayAvgVol": 42733.919000000009,
    "TwentyDayAvgVol": 39330.974499999989,
    "Concentration70": 0.0,
    "Concentration90": 0.0,
    "ConcentrationPrice": 0.0
  },
  {
    "Total_mv": 733344.4767,
    "Pe": 225.3488,
    "Pe_ttm": 225.3488,
    "TsCode": "002232.SZ",
    "TradeDate": "20260408",
    "Open": 17.6,
    "High": 17.95,
    "Low": 17.6,
    "Close": 17.95,
    "Vol": 46844.9,
    "Amount": 83492.351,
    "PctChg": 3.3391,
    "macdData": null,
    "kdjData": null,
    "FiveDayAvgPrice": 17.555999999999994,
    "TenDayAvgPrice": 17.478999999999992,
    "TwentyDayAvgPrice": 17.5055,
    "FiveDayAvgVol": 34576.628000000004,
    "TenDayAvgVol": 42655.179000000011,
    "TwentyDayAvgVol": 38849.624499999991,
    "Concentration70": 0.0,
    "Concentration90": 0.0,
    "ConcentrationPrice": 0.0
  },
  {
    "Total_mv": 709648.6663,
    "Pe": 218.0673,
    "Pe_ttm": 218.0673,
    "TsCode": "002232.SZ",
    "TradeDate": "20260407",
    "Open": 17.11,
    "High": 17.42,
    "Low": 17.04,
    "Close": 17.37,
    "Vol": 23570.0,
    "Amount": 40730.372,
    "PctChg": 1.6979,
    "macdData": null,
    "kdjData": null,
    "FiveDayAvgPrice": 17.521999999999995,
    "TenDayAvgPrice": 17.361999999999995,
    "TwentyDayAvgPrice": 17.5155,
    "FiveDayAvgVol": 37138.64,
    "TenDayAvgVol": 41932.189000000006,
    "TwentyDayAvgVol": 38206.99349999999,
    "Concentration70": 0.0,
    "Concentration90": 0.0,
    "ConcentrationPrice": 0.0
  },
  {
    "Total_mv": 697800.7611,
    "Pe": 214.4266,
    "Pe_ttm": 214.4266,
    "TsCode": "002232.SZ",
    "TradeDate": "20260403",
    "Open": 17.79,
    "High": 17.79,
    "Low": 17.05,
    "Close": 17.08,
    "Vol": 27375.02,
    "Amount": 47144.401,
    "PctChg": -2.9545,
    "macdData": null,
    "kdjData": null,
    "FiveDayAvgPrice": 17.649999999999995,
    "TenDayAvgPrice": 17.243999999999993,
    "TwentyDayAvgPrice": 17.55,
    "FiveDayAvgVol": 51414.226,
    "TenDayAvgVol": 45501.165000000008,
    "TwentyDayAvgVol": 39016.343499999988,
    "Concentration70": 0.0,
    "Concentration90": 0.0,
    "ConcentrationPrice": 0.0
  },
  {
    "Total_mv": 719045.2808,
    "Pe": 220.9548,
    "Pe_ttm": 220.9548,
    "TsCode": "002232.SZ",
    "TradeDate": "20260402",
    "Open": 17.72,
    "High": 17.89,
    "Low": 17.38,
    "Close": 17.6,
    "Vol": 35704.98,
    "Amount": 62803.128,
    "PctChg": -1.0124,
    "macdData": null,
    "kdjData": null,
    "FiveDayAvgPrice": 17.679999999999996,
    "TenDayAvgPrice": 17.239999999999995,
    "TwentyDayAvgPrice": 17.5895,
    "FiveDayAvgVol": 53428.930000000008,
    "TenDayAvgVol": 48298.057000000008,
    "TwentyDayAvgVol": 38867.742499999986,
    "Concentration70": 0.0,
    "Concentration90": 0.0,
    "ConcentrationPrice": 0.0
  },
  {
    "Total_mv": 726399.153,
    "Pe": 223.2146,
    "Pe_ttm": 223.2146,
    "TsCode": "002232.SZ",
    "TradeDate": "20260401",
    "Open": 17.96,
    "High": 18.04,
    "Low": 17.7,
    "Close": 17.78,
    "Vol": 39388.24,
    "Amount": 70134.579,
    "PctChg": 0.0,
    "macdData": null,
    "kdjData": null,
    "FiveDayAvgPrice": 17.525999999999993,
    "TenDayAvgPrice": 17.272999999999996,
    "TwentyDayAvgPrice": 17.5945,
    "FiveDayAvgVol": 51434.858,
    "TenDayAvgVol": 47517.359000000011,
    "TwentyDayAvgVol": 38673.872499999983,
    "Concentration70": 0.0,
    "Concentration90": 0.0,
    "ConcentrationPrice": 0.0
  }
]