[
  {
    "Total_mv": 4157515.805,
    "Pe": 50.1528,
    "Pe_ttm": 50.1528,
    "TsCode": "601126.SH",
    "TradeDate": "20260421",
    "Open": 48.65,
    "High": 50.34,
    "Low": 47.11,
    "Close": 49.9,
    "Vol": 311699.22,
    "Amount": 1520368.216,
    "PctChg": 2.1913,
    "macdData": null,
    "kdjData": null,
    "FiveDayAvgPrice": 0.0,
    "TenDayAvgPrice": 0.0,
    "TwentyDayAvgPrice": 0.0,
    "FiveDayAvgVol": 0.0,
    "TenDayAvgVol": 0.0,
    "TwentyDayAvgVol": 0.0,
    "Concentration70": 0.0,
    "Concentration90": 0.0,
    "ConcentrationPrice": 0.0
  },
  {
    "Total_mv": 4068366.6685,
    "Pe": 49.0773,
    "Pe_ttm": 49.0773,
    "TsCode": "601126.SH",
    "TradeDate": "20260420",
    "Open": 47.65,
    "High": 48.88,
    "Low": 46.98,
    "Close": 48.83,
    "Vol": 294525.14,
    "Amount": 1411173.736,
    "PctChg": 1.4544,
    "macdData": null,
    "kdjData": null,
    "FiveDayAvgPrice": 0.0,
    "TenDayAvgPrice": 0.0,
    "TwentyDayAvgPrice": 0.0,
    "FiveDayAvgVol": 0.0,
    "TenDayAvgVol": 0.0,
    "TwentyDayAvgVol": 0.0,
    "Concentration70": 0.0,
    "Concentration90": 0.0,
    "ConcentrationPrice": 0.0
  },
  {
    "Total_mv": 4010044.8035,
    "Pe": 48.3738,
    "Pe_ttm": 48.3738,
    "TsCode": "601126.SH",
    "TradeDate": "20260417",
    "Open": 46.45,
    "High": 49.0,
    "Low": 46.13,
    "Close": 48.13,
    "Vol": 346652.05,
    "Amount": 1652272.594,
    "PctChg": 3.5054,
    "macdData": null,
    "kdjData": null,
    "FiveDayAvgPrice": 0.0,
    "TenDayAvgPrice": 0.0,
    "TwentyDayAvgPrice": 0.0,
    "FiveDayAvgVol": 0.0,
    "TenDayAvgVol": 0.0,
    "TwentyDayAvgVol": 0.0,
    "Concentration70": 0.0,
    "Concentration90": 0.0,
    "ConcentrationPrice": 0.0
  },
  {
    "Total_mv": 3874238.175,
    "Pe": 46.7355,
    "Pe_ttm": 46.7355,
    "TsCode": "601126.SH",
    "TradeDate": "20260416",
    "Open": 45.71,
    "High": 46.5,
    "Low": 43.8,
    "Close": 46.5,
    "Vol": 318792.47,
    "Amount": 1446619.216,
    "PctChg": 3.2186,
    "macdData": null,
    "kdjData": null,
    "FiveDayAvgPrice": 0.0,
    "TenDayAvgPrice": 0.0,
    "TwentyDayAvgPrice": 0.0,
    "FiveDayAvgVol": 0.0,
    "TenDayAvgVol": 0.0,
    "TwentyDayAvgVol": 0.0,
    "Concentration70": 0.0,
    "Concentration90": 0.0,
    "ConcentrationPrice": 0.0
  },
  {
    "Total_mv": 3674277.495,
    "Pe": 44.3234,
    "Pe_ttm": 44.3234,
    "TsCode": "601126.SH",
    "TradeDate": "20260414",
    "Open": 43.95,
    "High": 44.75,
    "Low": 42.6,
    "Close": 44.1,
    "Vol": 327436.09,
    "Amount": 1434391.831,
    "PctChg": -0.5861,
    "macdData": null,
    "kdjData": null,
    "FiveDayAvgPrice": 0.0,
    "TenDayAvgPrice": 0.0,
    "TwentyDayAvgPrice": 0.0,
    "FiveDayAvgVol": 0.0,
    "TenDayAvgVol": 0.0,
    "TwentyDayAvgVol": 0.0,
    "Concentration70": 0.0,
    "Concentration90": 0.0,
    "ConcentrationPrice": 0.0
  },
  {
    "Total_mv": 3636784.8675,
    "Pe": 43.8711,
    "Pe_ttm": 43.8711,
    "TsCode": "601126.SH",
    "TradeDate": "20260410",
    "Open": 44.15,
    "High": 45.22,
    "Low": 43.07,
    "Close": 43.65,
    "Vol": 259001.11,
    "Amount": 1138198.226,
    "PctChg": -0.2969,
    "macdData": null,
    "kdjData": null,
    "FiveDayAvgPrice": 0.0,
    "TenDayAvgPrice": 0.0,
    "TwentyDayAvgPrice": 0.0,
    "FiveDayAvgVol": 0.0,
    "TenDayAvgVol": 0.0,
    "TwentyDayAvgVol": 0.0,
    "Concentration70": 0.0,
    "Concentration90": 0.0,
    "ConcentrationPrice": 0.0
  },
  {
    "Total_mv": 3645116.5625,
    "Pe": 43.9716,
    "Pe_ttm": 43.9716,
    "TsCode": "601126.SH",
    "TradeDate": "20260408",
    "Open": 41.66,
    "High": 43.8,
    "Low": 41.48,
    "Close": 43.75,
    "Vol": 327871.43,
    "Amount": 1399185.427,
    "PctChg": 9.6491,
    "macdData": null,
    "kdjData": null,
    "FiveDayAvgPrice": 0.0,
    "TenDayAvgPrice": 0.0,
    "TwentyDayAvgPrice": 0.0,
    "FiveDayAvgVol": 0.0,
    "TenDayAvgVol": 0.0,
    "TwentyDayAvgVol": 0.0,
    "Concentration70": 0.0,
    "Concentration90": 0.0,
    "ConcentrationPrice": 0.0
  },
  {
    "Total_mv": 3324346.305,
    "Pe": 40.1021,
    "Pe_ttm": 40.1021,
    "TsCode": "601126.SH",
    "TradeDate": "20260407",
    "Open": 41.86,
    "High": 42.15,
    "Low": 39.7,
    "Close": 39.9,
    "Vol": 210859.08,
    "Amount": 848712.897,
    "PctChg": -4.4082,
    "macdData": null,
    "kdjData": null,
    "FiveDayAvgPrice": 0.0,
    "TenDayAvgPrice": 0.0,
    "TwentyDayAvgPrice": 0.0,
    "FiveDayAvgVol": 0.0,
    "TenDayAvgVol": 0.0,
    "TwentyDayAvgVol": 0.0,
    "Concentration70": 0.0,
    "Concentration90": 0.0,
    "ConcentrationPrice": 0.0
  },
  {
    "Total_mv": 3477649.493,
    "Pe": 41.9514,
    "Pe_ttm": 41.9514,
    "TsCode": "601126.SH",
    "TradeDate": "20260403",
    "Open": 42.09,
    "High": 43.0,
    "Low": 41.2,
    "Close": 41.74,
    "Vol": 182512.89,
    "Amount": 767077.492,
    "PctChg": 0.3607,
    "macdData": null,
    "kdjData": null,
    "FiveDayAvgPrice": 0.0,
    "TenDayAvgPrice": 0.0,
    "TwentyDayAvgPrice": 0.0,
    "FiveDayAvgVol": 0.0,
    "TenDayAvgVol": 0.0,
    "TwentyDayAvgVol": 0.0,
    "Concentration70": 0.0,
    "Concentration90": 0.0,
    "ConcentrationPrice": 0.0
  },
  {
    "Total_mv": 3465151.9505,
    "Pe": 41.8007,
    "Pe_ttm": 41.8007,
    "TsCode": "601126.SH",
    "TradeDate": "20260402",
    "Open": 44.2,
    "High": 44.2,
    "Low": 41.21,
    "Close": 41.59,
    "Vol": 267718.21,
    "Amount": 1134243.737,
    "PctChg": -6.3499,
    "macdData": null,
    "kdjData": null,
    "FiveDayAvgPrice": 0.0,
    "TenDayAvgPrice": 0.0,
    "TwentyDayAvgPrice": 0.0,
    "FiveDayAvgVol": 0.0,
    "TenDayAvgVol": 0.0,
    "TwentyDayAvgVol": 0.0,
    "Concentration70": 0.0,
    "Concentration90": 0.0,
    "ConcentrationPrice": 0.0
  },
  {
    "Total_mv": 3700105.7495,
    "Pe": 44.635,
    "Pe_ttm": 44.635,
    "TsCode": "601126.SH",
    "TradeDate": "20260401",
    "Open": 44.5,
    "High": 44.92,
    "Low": 43.95,
    "Close": 44.41,
    "Vol": 214703.5,
    "Amount": 953657.942,
    "PctChg": 3.0873,
    "macdData": null,
    "kdjData": null,
    "FiveDayAvgPrice": 0.0,
    "TenDayAvgPrice": 0.0,
    "TwentyDayAvgPrice": 0.0,
    "FiveDayAvgVol": 0.0,
    "TenDayAvgVol": 0.0,
    "TwentyDayAvgVol": 0.0,
    "Concentration70": 0.0,
    "Concentration90": 0.0,
    "ConcentrationPrice": 0.0
  }
]