[
  {
    "Total_mv": 414251.13,
    "Pe": 0.0,
    "Pe_ttm": 217.6321,
    "TsCode": "600678.SH",
    "TradeDate": "20260421",
    "Open": 11.2,
    "High": 11.87,
    "Low": 11.2,
    "Close": 11.87,
    "Vol": 298356.01,
    "Amount": 352768.862,
    "PctChg": 10.0093,
    "macdData": null,
    "kdjData": null,
    "FiveDayAvgPrice": 10.849999999999996,
    "TenDayAvgPrice": 10.668,
    "TwentyDayAvgPrice": 10.557999999999996,
    "FiveDayAvgVol": 147983.402,
    "TenDayAvgVol": 113274.50100000002,
    "TwentyDayAvgVol": 112461.60900000001,
    "Concentration70": 0.0,
    "Concentration90": 0.0,
    "ConcentrationPrice": 0.0
  },
  {
    "Total_mv": 376560.21,
    "Pe": 0.0,
    "Pe_ttm": 197.8307,
    "TsCode": "600678.SH",
    "TradeDate": "20260420",
    "Open": 10.5,
    "High": 10.83,
    "Low": 10.42,
    "Close": 10.79,
    "Vol": 156563.0,
    "Amount": 167558.222,
    "PctChg": 3.0564,
    "macdData": null,
    "kdjData": null,
    "FiveDayAvgPrice": 10.579999999999997,
    "TenDayAvgPrice": 10.498,
    "TwentyDayAvgPrice": 10.467499999999998,
    "FiveDayAvgVol": 103717.6,
    "TenDayAvgVol": 91926.054000000033,
    "TwentyDayAvgVol": 104887.10900000001,
    "Concentration70": 0.0,
    "Concentration90": 0.0,
    "ConcentrationPrice": 0.0
  },
  {
    "Total_mv": 365392.53,
    "Pe": 0.0,
    "Pe_ttm": 191.9636,
    "TsCode": "600678.SH",
    "TradeDate": "20260417",
    "Open": 10.57,
    "High": 10.57,
    "Low": 10.3,
    "Close": 10.47,
    "Vol": 96417.0,
    "Amount": 100416.169,
    "PctChg": -1.1331,
    "macdData": null,
    "kdjData": null,
    "FiveDayAvgPrice": 10.515999999999996,
    "TenDayAvgPrice": 10.413,
    "TwentyDayAvgPrice": 10.453499999999996,
    "FiveDayAvgVol": 84250.000000000015,
    "TenDayAvgVol": 87480.013000000021,
    "TwentyDayAvgVol": 103667.629,
    "Concentration70": 0.0,
    "Concentration90": 0.0,
    "ConcentrationPrice": 0.0
  },
  {
    "Total_mv": 369580.41,
    "Pe": 0.0,
    "Pe_ttm": 194.1638,
    "TsCode": "600678.SH",
    "TradeDate": "20260416",
    "Open": 10.54,
    "High": 10.6,
    "Low": 10.42,
    "Close": 10.59,
    "Vol": 93461.0,
    "Amount": 98267.915,
    "PctChg": 0.5698,
    "macdData": null,
    "kdjData": null,
    "FiveDayAvgPrice": 10.511999999999997,
    "TenDayAvgPrice": 10.399,
    "TwentyDayAvgPrice": 10.480999999999998,
    "FiveDayAvgVol": 78683.000000000015,
    "TenDayAvgVol": 85536.214000000022,
    "TwentyDayAvgVol": 104901.879,
    "Concentration70": 0.0,
    "Concentration90": 0.0,
    "ConcentrationPrice": 0.0
  },
  {
    "Total_mv": 367486.47,
    "Pe": 0.0,
    "Pe_ttm": 193.0637,
    "TsCode": "600678.SH",
    "TradeDate": "20260415",
    "Open": 10.58,
    "High": 10.66,
    "Low": 10.47,
    "Close": 10.53,
    "Vol": 95120.0,
    "Amount": 100604.961,
    "PctChg": 0.0951,
    "macdData": null,
    "kdjData": null,
    "FiveDayAvgPrice": 10.471999999999998,
    "TenDayAvgPrice": 10.398,
    "TwentyDayAvgPrice": 10.522999999999998,
    "FiveDayAvgVol": 75363.200000000012,
    "TenDayAvgVol": 87244.014000000025,
    "TwentyDayAvgVol": 109706.62299999999,
    "Concentration70": 0.0,
    "Concentration90": 0.0,
    "ConcentrationPrice": 0.0
  },
  {
    "Total_mv": 367137.48,
    "Pe": 0.0,
    "Pe_ttm": 192.8804,
    "TsCode": "600678.SH",
    "TradeDate": "20260414",
    "Open": 10.52,
    "High": 10.56,
    "Low": 10.37,
    "Close": 10.52,
    "Vol": 77027.0,
    "Amount": 80440.314,
    "PctChg": 0.4776,
    "macdData": null,
    "kdjData": null,
    "FiveDayAvgPrice": 10.485999999999999,
    "TenDayAvgPrice": 10.395,
    "TwentyDayAvgPrice": 10.561499999999999,
    "FiveDayAvgVol": 78565.6,
    "TenDayAvgVol": 92533.222000000023,
    "TwentyDayAvgVol": 114831.30049999998,
    "Concentration70": 0.0,
    "Concentration90": 0.0,
    "ConcentrationPrice": 0.0
  },
  {
    "Total_mv": 365392.53,
    "Pe": 0.0,
    "Pe_ttm": 191.9636,
    "TsCode": "600678.SH",
    "TradeDate": "20260413",
    "Open": 10.36,
    "High": 10.5,
    "Low": 10.36,
    "Close": 10.47,
    "Vol": 59225.0,
    "Amount": 61759.755,
    "PctChg": 0.1914,
    "macdData": null,
    "kdjData": null,
    "FiveDayAvgPrice": 10.416,
    "TenDayAvgPrice": 10.391,
    "TwentyDayAvgPrice": 10.599499999999997,
    "FiveDayAvgVol": 80134.508,
    "TenDayAvgVol": 105027.29900000003,
    "TwentyDayAvgVol": 118005.82149999999,
    "Concentration70": 0.0,
    "Concentration90": 0.0,
    "ConcentrationPrice": 0.0
  },
  {
    "Total_mv": 364694.55,
    "Pe": 0.0,
    "Pe_ttm": 191.5969,
    "TsCode": "600678.SH",
    "TradeDate": "20260410",
    "Open": 10.39,
    "High": 10.58,
    "Low": 10.39,
    "Close": 10.45,
    "Vol": 68582.0,
    "Amount": 72008.43,
    "PctChg": 0.5775,
    "macdData": null,
    "kdjData": null,
    "FiveDayAvgPrice": 10.309999999999999,
    "TenDayAvgPrice": 10.414,
    "TwentyDayAvgPrice": 10.649999999999997,
    "FiveDayAvgVol": 90710.026,
    "TenDayAvgVol": 105649.01700000002,
    "TwentyDayAvgVol": 128467.64699999997,
    "Concentration70": 0.0,
    "Concentration90": 0.0,
    "ConcentrationPrice": 0.0
  },
  {
    "Total_mv": 362600.61,
    "Pe": 0.0,
    "Pe_ttm": 190.4969,
    "TsCode": "600678.SH",
    "TradeDate": "20260409",
    "Open": 10.58,
    "High": 10.59,
    "Low": 10.35,
    "Close": 10.39,
    "Vol": 76862.0,
    "Amount": 80185.02,
    "PctChg": -1.9811,
    "macdData": null,
    "kdjData": null,
    "FiveDayAvgPrice": 10.286,
    "TenDayAvgPrice": 10.426,
    "TwentyDayAvgPrice": 10.686499999999999,
    "FiveDayAvgVol": 92389.428,
    "TenDayAvgVol": 106615.21700000002,
    "TwentyDayAvgVol": 129909.53899999996,
    "Concentration70": 0.0,
    "Concentration90": 0.0,
    "ConcentrationPrice": 0.0
  },
  {
    "Total_mv": 369929.4,
    "Pe": 0.0,
    "Pe_ttm": 194.3471,
    "TsCode": "600678.SH",
    "TradeDate": "20260408",
    "Open": 10.29,
    "High": 10.6,
    "Low": 10.29,
    "Close": 10.6,
    "Vol": 111132.0,
    "Amount": 116469.022,
    "PctChg": 4.2281,
    "macdData": null,
    "kdjData": null,
    "FiveDayAvgPrice": 10.324,
    "TenDayAvgPrice": 10.459,
    "TwentyDayAvgPrice": 10.735,
    "FiveDayAvgVol": 99124.828000000009,
    "TenDayAvgVol": 108408.61700000001,
    "TwentyDayAvgVol": 130946.84849999996,
    "Concentration70": 0.0,
    "Concentration90": 0.0,
    "ConcentrationPrice": 0.0
  },
  {
    "Total_mv": 354922.83,
    "Pe": 0.0,
    "Pe_ttm": 186.4632,
    "TsCode": "600678.SH",
    "TradeDate": "20260407",
    "Open": 10.0,
    "High": 10.22,
    "Low": 9.97,
    "Close": 10.17,
    "Vol": 84871.54,
    "Amount": 86017.872,
    "PctChg": 2.3139,
    "macdData": null,
    "kdjData": null,
    "FiveDayAvgPrice": 10.303999999999998,
    "TenDayAvgPrice": 10.448,
    "TwentyDayAvgPrice": 10.78,
    "FiveDayAvgVol": 106500.844,
    "TenDayAvgVol": 111648.71700000002,
    "TwentyDayAvgVol": 129910.73349999997,
    "Concentration70": 0.0,
    "Concentration90": 0.0,
    "ConcentrationPrice": 0.0
  },
  {
    "Total_mv": 346896.06,
    "Pe": 0.0,
    "Pe_ttm": 182.2463,
    "TsCode": "600678.SH",
    "TradeDate": "20260403",
    "Open": 10.33,
    "High": 10.39,
    "Low": 9.93,
    "Close": 9.94,
    "Vol": 112102.59,
    "Amount": 112608.851,
    "PctChg": -3.7754,
    "macdData": null,
    "kdjData": null,
    "FiveDayAvgPrice": 10.366,
    "TenDayAvgPrice": 10.437000000000001,
    "TwentyDayAvgPrice": 10.841000000000001,
    "FiveDayAvgVol": 129920.09,
    "TenDayAvgVol": 117848.16400000002,
    "TwentyDayAvgVol": 131271.64399999997,
    "Concentration70": 0.0,
    "Concentration90": 0.0,
    "ConcentrationPrice": 0.0
  },
  {
    "Total_mv": 360506.67,
    "Pe": 0.0,
    "Pe_ttm": 189.3968,
    "TsCode": "600678.SH",
    "TradeDate": "20260402",
    "Open": 10.52,
    "High": 10.57,
    "Low": 10.27,
    "Close": 10.33,
    "Vol": 76979.01,
    "Amount": 79971.394,
    "PctChg": -2.3629,
    "macdData": null,
    "kdjData": null,
    "FiveDayAvgPrice": 10.518,
    "TenDayAvgPrice": 10.494000000000002,
    "TwentyDayAvgPrice": 10.917000000000002,
    "FiveDayAvgVol": 120588.008,
    "TenDayAvgVol": 119855.245,
    "TwentyDayAvgVol": 130768.56449999998,
    "Concentration70": 0.0,
    "Concentration90": 0.0,
    "ConcentrationPrice": 0.0
  },
  {
    "Total_mv": 369231.42,
    "Pe": 0.0,
    "Pe_ttm": 193.9804,
    "TsCode": "600678.SH",
    "TradeDate": "20260401",
    "Open": 10.71,
    "High": 10.83,
    "Low": 10.46,
    "Close": 10.58,
    "Vol": 110539.0,
    "Amount": 116994.322,
    "PctChg": 0.7619,
    "macdData": null,
    "kdjData": null,
    "FiveDayAvgPrice": 10.566,
    "TenDayAvgPrice": 10.563,
    "TwentyDayAvgPrice": 10.966000000000001,
    "FiveDayAvgVol": 120841.00600000001,
    "TenDayAvgVol": 124267.544,
    "TwentyDayAvgVol": 132643.7365,
    "Concentration70": 0.0,
    "Concentration90": 0.0,
    "ConcentrationPrice": 0.0
  }
]