[
  {
    "Total_mv": 419502.3907,
    "Pe": 0.0,
    "Pe_ttm": 0.0,
    "TsCode": "002995.SZ",
    "TradeDate": "20260421",
    "Open": 24.02,
    "High": 24.1,
    "Low": 23.4,
    "Close": 23.64,
    "Vol": 105291.8,
    "Amount": 248941.893,
    "PctChg": -2.5155,
    "macdData": null,
    "kdjData": null,
    "FiveDayAvgPrice": 23.866000000000007,
    "TenDayAvgPrice": 24.161000000000008,
    "TwentyDayAvgPrice": 23.553,
    "FiveDayAvgVol": 139071.498,
    "TenDayAvgVol": 166384.17300000007,
    "TwentyDayAvgVol": 184922.04550000012,
    "Concentration70": 0.0,
    "Concentration90": 0.0,
    "ConcentrationPrice": 0.0
  },
  {
    "Total_mv": 430327.114,
    "Pe": 0.0,
    "Pe_ttm": 0.0,
    "TsCode": "002995.SZ",
    "TradeDate": "20260420",
    "Open": 23.7,
    "High": 24.35,
    "Low": 23.53,
    "Close": 24.25,
    "Vol": 132324.0,
    "Amount": 318697.591,
    "PctChg": 1.5069,
    "macdData": null,
    "kdjData": null,
    "FiveDayAvgPrice": 24.000000000000007,
    "TenDayAvgPrice": 24.048000000000005,
    "TwentyDayAvgPrice": 23.5455,
    "FiveDayAvgVol": 151813.17599999998,
    "TenDayAvgVol": 172880.72200000007,
    "TwentyDayAvgVol": 181886.60550000012,
    "Concentration70": 0.0,
    "Concentration90": 0.0,
    "ConcentrationPrice": 0.0
  },
  {
    "Total_mv": 423938.7527,
    "Pe": 0.0,
    "Pe_ttm": 0.0,
    "TsCode": "002995.SZ",
    "TradeDate": "20260417",
    "Open": 24.05,
    "High": 24.09,
    "Low": 23.33,
    "Close": 23.89,
    "Vol": 125581.89,
    "Amount": 297459.705,
    "PctChg": -1.4032,
    "macdData": null,
    "kdjData": null,
    "FiveDayAvgPrice": 23.982000000000006,
    "TenDayAvgPrice": 23.808000000000003,
    "TwentyDayAvgPrice": 23.638,
    "FiveDayAvgVol": 149987.97599999997,
    "TenDayAvgVol": 174827.91100000005,
    "TwentyDayAvgVol": 187730.22100000014,
    "Concentration70": 0.0,
    "Concentration90": 0.0,
    "ConcentrationPrice": 0.0
  },
  {
    "Total_mv": 429972.205,
    "Pe": 0.0,
    "Pe_ttm": 0.0,
    "TsCode": "002995.SZ",
    "TradeDate": "20260416",
    "Open": 23.73,
    "High": 24.39,
    "Low": 23.29,
    "Close": 24.23,
    "Vol": 176267.0,
    "Amount": 423546.123,
    "PctChg": 3.9022,
    "macdData": null,
    "kdjData": null,
    "FiveDayAvgPrice": 24.046000000000006,
    "TenDayAvgPrice": 23.747000000000003,
    "TwentyDayAvgPrice": 23.778000000000002,
    "FiveDayAvgVol": 160176.22599999997,
    "TenDayAvgVol": 180272.72200000007,
    "TwentyDayAvgVol": 197986.17450000014,
    "Concentration70": 0.0,
    "Concentration90": 0.0,
    "ConcentrationPrice": 0.0
  },
  {
    "Total_mv": 413823.8474,
    "Pe": 0.0,
    "Pe_ttm": 0.0,
    "TsCode": "002995.SZ",
    "TradeDate": "20260415",
    "Open": 24.29,
    "High": 24.29,
    "Low": 23.24,
    "Close": 23.32,
    "Vol": 155892.8,
    "Amount": 367523.041,
    "PctChg": -4.0724,
    "macdData": null,
    "kdjData": null,
    "FiveDayAvgPrice": 24.168000000000006,
    "TenDayAvgPrice": 23.748000000000005,
    "TwentyDayAvgPrice": 23.872500000000002,
    "FiveDayAvgVol": 185206.322,
    "TenDayAvgVol": 193847.60900000005,
    "TwentyDayAvgVol": 202856.64650000012,
    "Concentration70": 0.0,
    "Concentration90": 0.0,
    "ConcentrationPrice": 0.0
  },
  {
    "Total_mv": 431391.8409,
    "Pe": 0.0,
    "Pe_ttm": 0.0,
    "TsCode": "002995.SZ",
    "TradeDate": "20260414",
    "Open": 24.41,
    "High": 24.65,
    "Low": 24.01,
    "Close": 24.31,
    "Vol": 169000.19,
    "Amount": 411475.347,
    "PctChg": 0.6209,
    "macdData": null,
    "kdjData": null,
    "FiveDayAvgPrice": 24.45600000000001,
    "TenDayAvgPrice": 23.882000000000005,
    "TwentyDayAvgPrice": 24.012000000000004,
    "FiveDayAvgVol": 193696.84799999994,
    "TenDayAvgVol": 191577.61600000007,
    "TwentyDayAvgVol": 217822.56950000013,
    "Concentration70": 0.0,
    "Concentration90": 0.0,
    "ConcentrationPrice": 0.0
  },
  {
    "Total_mv": 428730.0237,
    "Pe": 0.0,
    "Pe_ttm": 0.0,
    "TsCode": "002995.SZ",
    "TradeDate": "20260413",
    "Open": 24.26,
    "High": 24.33,
    "Low": 23.87,
    "Close": 24.16,
    "Vol": 123198.0,
    "Amount": 297300.172,
    "PctChg": -0.2065,
    "macdData": null,
    "kdjData": null,
    "FiveDayAvgPrice": 24.096000000000011,
    "TenDayAvgPrice": 23.693000000000005,
    "TwentyDayAvgPrice": 24.035000000000004,
    "FiveDayAvgVol": 193948.26799999995,
    "TenDayAvgVol": 195449.08800000005,
    "TwentyDayAvgVol": 219474.77750000014,
    "Concentration70": 0.0,
    "Concentration90": 0.0,
    "ConcentrationPrice": 0.0
  },
  {
    "Total_mv": 429617.2961,
    "Pe": 0.0,
    "Pe_ttm": 0.0,
    "TsCode": "002995.SZ",
    "TradeDate": "20260410",
    "Open": 25.11,
    "High": 25.2,
    "Low": 24.21,
    "Close": 24.21,
    "Vol": 176523.14,
    "Amount": 433408.586,
    "PctChg": -2.5362,
    "macdData": null,
    "kdjData": null,
    "FiveDayAvgPrice": 23.634000000000007,
    "TenDayAvgPrice": 23.642000000000007,
    "TwentyDayAvgPrice": 23.953,
    "FiveDayAvgVol": 199667.84599999996,
    "TenDayAvgVol": 194876.22400000007,
    "TwentyDayAvgVol": 216792.34500000012,
    "Concentration70": 0.0,
    "Concentration90": 0.0,
    "ConcentrationPrice": 0.0
  },
  {
    "Total_mv": 440796.9283,
    "Pe": 0.0,
    "Pe_ttm": 0.0,
    "TsCode": "002995.SZ",
    "TradeDate": "20260409",
    "Open": 24.75,
    "High": 25.28,
    "Low": 24.16,
    "Close": 24.84,
    "Vol": 301417.48,
    "Amount": 745017.687,
    "PctChg": 0.3231,
    "macdData": null,
    "kdjData": null,
    "FiveDayAvgPrice": 23.448000000000008,
    "TenDayAvgPrice": 23.371000000000006,
    "TwentyDayAvgPrice": 23.8895,
    "FiveDayAvgVol": 200369.21799999994,
    "TenDayAvgVol": 195587.53100000005,
    "TwentyDayAvgVol": 211312.35800000009,
    "Concentration70": 0.0,
    "Concentration90": 0.0,
    "ConcentrationPrice": 0.0
  },
  {
    "Total_mv": 439377.2925,
    "Pe": 0.0,
    "Pe_ttm": 0.0,
    "TsCode": "002995.SZ",
    "TradeDate": "20260408",
    "Open": 23.18,
    "High": 24.76,
    "Low": 22.76,
    "Close": 24.76,
    "Vol": 198345.43,
    "Amount": 475486.545,
    "PctChg": 9.9956,
    "macdData": null,
    "kdjData": null,
    "FiveDayAvgPrice": 23.328000000000007,
    "TenDayAvgPrice": 23.132000000000005,
    "TwentyDayAvgPrice": 23.812000000000005,
    "FiveDayAvgVol": 202488.89599999995,
    "TenDayAvgVol": 191204.85100000005,
    "TwentyDayAvgVol": 199967.38400000008,
    "Concentration70": 0.0,
    "Concentration90": 0.0,
    "ConcentrationPrice": 0.0
  },
  {
    "Total_mv": 399450.0345,
    "Pe": 0.0,
    "Pe_ttm": 0.0,
    "TsCode": "002995.SZ",
    "TradeDate": "20260407",
    "Open": 22.11,
    "High": 23.8,
    "Low": 21.92,
    "Close": 22.51,
    "Vol": 170257.29,
    "Amount": 386102.918,
    "PctChg": 3.0206,
    "macdData": null,
    "kdjData": null,
    "FiveDayAvgPrice": 23.308000000000003,
    "TenDayAvgPrice": 22.945000000000004,
    "TwentyDayAvgPrice": 23.761000000000003,
    "FiveDayAvgVol": 189458.38399999993,
    "TenDayAvgVol": 203459.91800000006,
    "TwentyDayAvgVol": 194698.29350000009,
    "Concentration70": 0.0,
    "Concentration90": 0.0,
    "ConcentrationPrice": 0.0
  },
  {
    "Total_mv": 387738.0388,
    "Pe": 0.0,
    "Pe_ttm": 0.0,
    "TsCode": "002995.SZ",
    "TradeDate": "20260403",
    "Open": 23.69,
    "High": 23.88,
    "Low": 21.84,
    "Close": 21.85,
    "Vol": 151795.89,
    "Amount": 339129.866,
    "PctChg": -6.1426,
    "macdData": null,
    "kdjData": null,
    "FiveDayAvgPrice": 23.290000000000003,
    "TenDayAvgPrice": 23.043000000000006,
    "TwentyDayAvgPrice": 23.820500000000003,
    "FiveDayAvgVol": 196949.90799999994,
    "TenDayAvgVol": 190892.48900000006,
    "TwentyDayAvgVol": 191426.80100000006,
    "Concentration70": 0.0,
    "Concentration90": 0.0,
    "ConcentrationPrice": 0.0
  },
  {
    "Total_mv": 413114.0294,
    "Pe": 0.0,
    "Pe_ttm": 0.0,
    "TsCode": "002995.SZ",
    "TradeDate": "20260402",
    "Open": 24.13,
    "High": 24.24,
    "Low": 23.13,
    "Close": 23.28,
    "Vol": 180030.0,
    "Amount": 422981.22,
    "PctChg": -3.9604,
    "macdData": null,
    "kdjData": null,
    "FiveDayAvgPrice": 23.650000000000002,
    "TenDayAvgPrice": 23.468000000000007,
    "TwentyDayAvgPrice": 23.896500000000003,
    "FiveDayAvgVol": 190084.60199999993,
    "TenDayAvgVol": 200632.53100000005,
    "TwentyDayAvgVol": 187628.38800000006,
    "Concentration70": 0.0,
    "Concentration90": 0.0,
    "ConcentrationPrice": 0.0
  },
  {
    "Total_mv": 430149.6595,
    "Pe": 0.0,
    "Pe_ttm": 0.0,
    "TsCode": "002995.SZ",
    "TradeDate": "20260401",
    "Open": 25.2,
    "High": 25.4,
    "Low": 24.0,
    "Close": 24.24,
    "Vol": 312015.87,
    "Amount": 762443.639,
    "PctChg": -1.7032,
    "macdData": null,
    "kdjData": null,
    "FiveDayAvgPrice": 23.294000000000004,
    "TenDayAvgPrice": 23.809000000000005,
    "TwentyDayAvgPrice": 23.898000000000003,
    "FiveDayAvgVol": 190805.84399999992,
    "TenDayAvgVol": 215699.62700000004,
    "TwentyDayAvgVol": 182837.84650000004,
    "Concentration70": 0.0,
    "Concentration90": 0.0,
    "ConcentrationPrice": 0.0
  }
]